FlaskFloodgate/__init__.py
FlaskFloodgate/handlers.py
FlaskFloodgate-1.2.dist-info/LICENSE
FlaskFloodgate-1.2.dist-info/METADATA
FlaskFloodgate-1.2.dist-info/WHEEL
FlaskFloodgate-1.2.dist-info/top_level.txt
FlaskFloodgate-1.2.dist-info/RECORD
