Metadata-Version: 2.1
Name: FlaskFloodgate
Version: 1.2
Summary: A small customizable package to rate-limit your Flask endpoints.
Author-email: Evscion <ivoscev@example.com>
Project-URL: Homepage, https://github.com/Evscion/FlaskFloodgate
Project-URL: Issues, https://github.com/Evscion/FlaskFloodgate/issues
Keywords: flask,rate-limit,floodgate,ip-limit
Classifier: Programming Language :: Python :: 3
Classifier: License :: OSI Approved :: MIT License
Classifier: Operating System :: OS Independent
Requires-Python: >=3.8
License-File: LICENSE
Requires-Dist: flask
Requires-Dist: redis
